shared_lock/test.py
shared_lock/__init__.py
shared_lock/process_lock.py
shared_lock/lock.py
shared_lock/tests/test_process_lock.py
shared_lock/tests/__init__.py
shared_lock/tests/test_lock.py
shared_lock-0.2.1.dist-info/pbr.json
shared_lock-0.2.1.dist-info/RECORD
shared_lock-0.2.1.dist-info/DESCRIPTION.rst
shared_lock-0.2.1.dist-info/METADATA
shared_lock-0.2.1.dist-info/top_level.txt
shared_lock-0.2.1.dist-info/metadata.json
shared_lock-0.2.1.dist-info/WHEEL
