Metadata-Version: 2.0
Name: shared-lock
Version: 0.2.1
Summary: A python package that provides useful locks.
Home-page: https://github.com/harlowja/SharedLock
Author: Joshua Harlow
Author-email: harlowja@yahoo-inc.com
License: ASL 2.0
Keywords: locks thread threads interprocess
Platform: UNKNOWN
Classifier: Development Status :: 4 - Beta
Classifier: Topic :: Utilities
Classifier: License :: OSI Approved :: Apache Software License
Classifier: Operating System :: POSIX :: Linux
Classifier: Programming Language :: Python
Classifier: Programming Language :: Python :: 2
Classifier: Programming Language :: Python :: 2.6
Classifier: Programming Language :: Python :: 2.7
Classifier: Programming Language :: Python :: 3
Classifier: Programming Language :: Python :: 3.4
Requires-Dist: oslo.utils (>=1.4.0)
Requires-Dist: six
